multi_view_network/__init__.py
multi_view_network/models.py
multi_view_network/utils.py
multi_view_network-1.0.dist-info/METADATA
multi_view_network-1.0.dist-info/RECORD
multi_view_network-1.0.dist-info/WHEEL
multi_view_network-1.0.dist-info/top_level.txt
tests/__init__.py
tests/models_tests.py
tests/utils_tests.py
