Metadata-Version: 2.1
Name: multi-view-network
Version: 1.0
Summary: Keras implementation of Multi-View Network by Guo et al.
Home-page: https://github.com/annoys-parrot/multi_view_network
Author: Alessandro Scoccia Pappagallo
Author-email: aless@ndro.xyz
License: UNKNOWN
Keywords: keras tensorflow machine-learning NLP research
Platform: UNKNOWN
Classifier: Programming Language :: Python :: 3
Classifier: License :: OSI Approved :: MIT License
Classifier: Operating System :: OS Independent
Requires-Dist: tensorflow
Requires-Dist: keras
